Flask_Simple_Serializer-1.1.3.dist-info/DESCRIPTION.rst
Flask_Simple_Serializer-1.1.3.dist-info/METADATA
Flask_Simple_Serializer-1.1.3.dist-info/RECORD
Flask_Simple_Serializer-1.1.3.dist-info/WHEEL
Flask_Simple_Serializer-1.1.3.dist-info/metadata.json
Flask_Simple_Serializer-1.1.3.dist-info/top_level.txt
flask_simple_serializer/__init__.py
flask_simple_serializer/decorators.py
flask_simple_serializer/fields.py
flask_simple_serializer/response.py
flask_simple_serializer/serializers.py
flask_simple_serializer/status_codes.py
