Metadata-Version: 2.0
Name: Flask-Simple-Serializer
Version: 1.1.3
Summary: Simple Serializers for API validations
Home-page: https://github.com/marcosschroh/Flask-Simple-Serializer
Author: Marcos Schroh
Author-email: marcos.06sch@gmail.com
License: BSD
Platform: any
Classifier: Environment :: Web Environment
Classifier: Intended Audience :: Developers
Classifier: License :: OSI Approved :: BSD License
Classifier: Operating System :: OS Independent
Classifier: Programming Language :: Python
Classifier: Framework :: Flask
Classifier: Topic :: Internet :: WWW/HTTP :: Dynamic Content
Classifier: Topic :: Software Development :: Libraries :: Python Modules
Requires-Dist: Flask
Requires-Dist: WTForms
Requires-Dist: WTForms-Alchemy
Requires-Dist: Werkzeug
